Metadata-Version: 2.1
Name: IRTools
Version: 1.2.2.1
Summary: a computational toolset for detection and analysis of intron retention from RNA-Seq libraries
Home-page: https://github.com/WeiqunPengLab/IRTools/
Author: Zhouhao Zeng, Andy Cao
Author-email: zzhlbj23@gwmail.gwu.edu, acao3@email.gwu.edu
Classifier: Development Status :: 4 - Beta
Classifier: Environment :: Console
Classifier: Intended Audience :: Developers
Classifier: Intended Audience :: Science/Research
Classifier: License :: OSI Approved :: GNU General Public License (GPL)
Classifier: Operating System :: MacOS :: MacOS X
Classifier: Operating System :: POSIX
Classifier: Topic :: Scientific/Engineering :: Bio-Informatics
Classifier: Programming Language :: Python
License-File: LICENSE
Requires-Dist: numpy
Requires-Dist: scipy
Requires-Dist: pandas
Requires-Dist: networkx
Requires-Dist: bx-python
Requires-Dist: HTSeq (==0.13.5)
Requires-Dist: pysam (==0.19.1)
